shuffdi/LICENSE
shuffdi/README.MD
shuffdi/__init__.py
shuffdi/requirements.txt
shuffdi/thirdparty.json
shuffdi-0.10.dist-info/LICENSE.rst
shuffdi-0.10.dist-info/METADATA
shuffdi-0.10.dist-info/WHEEL
shuffdi-0.10.dist-info/top_level.txt
shuffdi-0.10.dist-info/RECORD
